pynner/__init__.py
pynner/gmm.py
pynner/util.py
pynner/net/__init__.py
pynner/net/affinity.py
pynner/net/from_df.py
pynner-0.0.3.dist-info/LICENSE
pynner-0.0.3.dist-info/METADATA
pynner-0.0.3.dist-info/WHEEL
pynner-0.0.3.dist-info/top_level.txt
pynner-0.0.3.dist-info/RECORD
