Metadata-Version: 2.1
Name: pynner
Version: 0.0.3
Summary: Visualization utils.
Home-page: https://github.com/thorwhalen/newut/tree/master/pynner
Author: Thor Whalen
License: mit
Platform: any
License-File: LICENSE
